sentinel_mas/__init__.py
sentinel_mas/config.py
sentinel_mas/timewin.py
sentinel_mas/utils.py
sentinel_mas/agents/__init__.py
sentinel_mas/agents/crew.py
sentinel_mas/agents/crew_agents.py
sentinel_mas/agents/crew_with_guard.py
sentinel_mas/agents/loader.py
sentinel_mas/agents/runtime.py
sentinel_mas/agents/agent_configs/events.yml
sentinel_mas/agents/agent_configs/faq_sop.yml
sentinel_mas/agents/agent_configs/router.yml
sentinel_mas/agents/agent_configs/tracking.yml
sentinel_mas/data/pg_backup_18-oct-2025.sql
sentinel_mas/data/kb/sentinel_sop_kb.jsonl
sentinel_mas/policy_sentinel/__init__.py
sentinel_mas/policy_sentinel/audit.py
sentinel_mas/policy_sentinel/runtime.py
sentinel_mas/policy_sentinel/secure_executor.py
sentinel_mas/policy_sentinel/secure_tool_node.py
sentinel_mas/policy_sentinel/configs/injection_policy.yml
sentinel_mas/policy_sentinel/configs/rbac_policy.yml
sentinel_mas/policy_sentinel/configs/redactor_policy.yml
sentinel_mas/policy_sentinel/policy/__init__.py
sentinel_mas/policy_sentinel/policy/injection_guard.py
sentinel_mas/policy_sentinel/policy/rbac_loader.py
sentinel_mas/policy_sentinel/policy/security_redactor.py
sentinel_mas/prompts/cctv_events.yaml
sentinel_mas/prompts/faq_sop.yaml
sentinel_mas/prompts/router.yaml
sentinel_mas/prompts/tracking_ops.yaml
sentinel_mas/state/graph_state.py
sentinel_mas/state/utils.py
sentinel_mas/tools/__init__.py
sentinel_mas/tools/events_tools.py
sentinel_mas/tools/loader.py
sentinel_mas/tools/sop_tools.py
sentinel_mas/tools/tracking_tools.py
sentinel_mas-0.1.0.dist-info/METADATA
sentinel_mas-0.1.0.dist-info/WHEEL
sentinel_mas-0.1.0.dist-info/top_level.txt
sentinel_mas-0.1.0.dist-info/RECORD
