Metadata-Version: 2.4
Name: sentinel-mas
Version: 0.1.0
Summary: A Multi-Agent System for intelligent task processing
Author-email: Kelvin Lee <chekeng82@gmail.com>
License: MIT
Project-URL: Homepage, https://github.com/A0291221R/sentinel_mas
Project-URL: Documentation, https://github.com/A0291221R/sentinel_mas
Project-URL: Repository, https://github.com/A0291221R/sentinel_mas
Classifier: Development Status :: 3 - Alpha
Classifier: Intended Audience :: Developers
Classifier: License :: OSI Approved :: MIT License
Classifier: Programming Language :: Python :: 3
Requires-Python: >=3.12
Requires-Dist: bandit>=1.7.7
Requires-Dist: black>=23.9.0
Requires-Dist: coverage>=7.3.0
Requires-Dist: fastapi>=0.119.0
Requires-Dist: fastmcp>=2.12.5
Requires-Dist: flake8>=6.1.0
Requires-Dist: freezegun>=1.5
Requires-Dist: gradio>=5.49.1
Requires-Dist: httpx>=0.28.1
Requires-Dist: isort>=5.13.0
Requires-Dist: jinja2>=3.1.6
Requires-Dist: langchain>=0.3.27
Requires-Dist: langchain-anthropic>=1.0.0
Requires-Dist: langchain-community>=0.3.31
Requires-Dist: langchain-core>=0.3.79
Requires-Dist: langchain-mcp-adapters>=0.1.11
Requires-Dist: langchain-openai>=0.3.35
Requires-Dist: langchain-tavily>=0.2.12
Requires-Dist: langgraph>=0.6.10
Requires-Dist: langgraph-cli[inmem]>=0.4.3
Requires-Dist: matplotlib>=3.10.7
Requires-Dist: mypy>=1.9.0
Requires-Dist: openai>=2.3.0
Requires-Dist: pandas>=2.3.3
Requires-Dist: pip>=25.2
Requires-Dist: psycopg[binary]>=3.2.10
Requires-Dist: pushover>=0.5
Requires-Dist: pydantic>=2
Requires-Dist: pytest>=7.4.0
Requires-Dist: pytest-cov>=4.1.0
Requires-Dist: pytest-mock>=3.10.0
Requires-Dist: pytest-xdist>=3.3.0
Requires-Dist: python-dateutil>=2.9.0.post0
Requires-Dist: python-jose[cryptography]>=3.5.0
Requires-Dist: pytz>=2025.2
Requires-Dist: pyyaml>=6.0
Requires-Dist: requests>=2.32.5
Requires-Dist: respx>=0.22.0
Requires-Dist: safety>=2.3.5
Requires-Dist: sentence-transformers>=5.1.1
Requires-Dist: sqlalchemy>=2.0.44
Requires-Dist: streamlit>=1.50.0
Requires-Dist: tavily-python>=0.7.12
Requires-Dist: tiktoken>=0.12.0
Requires-Dist: types-python-jose>=3.5.0.20250531
Requires-Dist: uvicorn[standard]>=0.37.0
Requires-Dist: yfinance>=0.2.66
Provides-Extra: dev
Requires-Dist: pytest>=7.4.0; extra == "dev"
Requires-Dist: pytest-cov>=4.1.0; extra == "dev"
Requires-Dist: pytest-xdist>=3.3.0; extra == "dev"
Requires-Dist: black>=23.0.0; extra == "dev"
Requires-Dist: isort>=5.12.0; extra == "dev"
Requires-Dist: flake8>=6.0.0; extra == "dev"
Requires-Dist: mypy>=1.5.0; extra == "dev"
Requires-Dist: bandit>=1.7.5; extra == "dev"
Requires-Dist: safety>=2.3.5; extra == "dev"
